securepassgen_advanced/__init__.py
securepassgen_advanced/cli.py
securepassgen_advanced/generator.py
securepassgen_advanced-1.0.2.dist-info/METADATA
securepassgen_advanced-1.0.2.dist-info/WHEEL
securepassgen_advanced-1.0.2.dist-info/entry_points.txt
securepassgen_advanced-1.0.2.dist-info/top_level.txt
securepassgen_advanced-1.0.2.dist-info/RECORD
