Metadata-Version: 2.4
Name: securepassgen-advanced
Version: 1.0.2
Summary: Advanced password generator library
Author: cipherh4ck
Author-email: emerickcipher@gmail.com
Requires-Python: >=3.6
Dynamic: author
Dynamic: author-email
Dynamic: requires-python
Dynamic: summary
